sb_loki_handler/__init__.py
sb_loki_handler/handlers.py
sb_loki_handler/py.typed
sb_loki_handler-1.0.0.dist-info/METADATA
sb_loki_handler-1.0.0.dist-info/WHEEL
sb_loki_handler-1.0.0.dist-info/top_level.txt
sb_loki_handler-1.0.0.dist-info/RECORD
