Metadata-Version: 2.4
Name: sb-loki-handler
Version: 1.0.0
Summary: Typed loki handler for logging
Author-email: Pradish Bijukchhe <pradish@sandbox.com.np>
License-Expression: MIT
Project-URL: Homepage, https://github.com/sandbox-pokhara/sb-loki-handler
Project-URL: Issues, https://github.com/sandbox-pokhara/sb-loki-handler/issues
Classifier: Programming Language :: Python :: 3
Requires-Python: >=3.6
Requires-Dist: httpx>=0.20.0
Provides-Extra: pre-commit
Requires-Dist: pre-commit; extra == "pre-commit"
